CHANGES.txt
DEPENDENCES.txt
README.txt
setup.py
src/ng/__init__.py
src/ng.schema.egg-info/PKG-INFO
src/ng.schema.egg-info/SOURCES.txt
src/ng.schema.egg-info/dependency_links.txt
src/ng.schema.egg-info/namespace_packages.txt
src/ng.schema.egg-info/not-zip-safe
src/ng.schema.egg-info/requires.txt
src/ng.schema.egg-info/top_level.txt
src/ng/schema/__init__.py
src/ng/schema/configure.zcml
src/ng/schema/ng.schema.txt
src/ng/schema/dropdowndatewidget/__init__.py
src/ng/schema/dropdowndatewidget/configure.zcml
src/ng/schema/dropdowndatewidget/dropdowndatewidget.py
src/ng/schema/etc/ng.schema-configure.zcml
src/ng/schema/floatdaytime/__init__.py
src/ng/schema/floatdaytime/configure.zcml
src/ng/schema/floatdaytime/floatdaytime.py
src/ng/schema/interfaceswitcher/__init__.py
src/ng/schema/interfaceswitcher/configure.zcml
src/ng/schema/interfaceswitcher/interfacechoicefield.py
src/ng/schema/interfaceswitcher/interfaces.py
src/ng/schema/interfaceswitcher/interfacesetfield.py
src/ng/schema/interfaceswitcher/interfacevocabulary.py
src/ng/schema/multiselectwidget/__init__.py
src/ng/schema/multiselectwidget/configure.zcml
src/ng/schema/multiselectwidget/multiselectwidget.pt
src/ng/schema/multiselectwidget/multiselectwidget.py
src/ng/schema/multiselectwidget/demo/__init__.py
src/ng/schema/multiselectwidget/demo/configure.zcml
src/ng/schema/multiselectwidget/demo/demomultiselectwidget.py
src/ng/schema/multiselectwidget/demo/interfaces.py
src/ng/schema/multiselectwidget/demo/browser/__init__.py
src/ng/schema/multiselectwidget/demo/browser/configure.zcml
src/ng/schema/principalidwidget/__init__.py
src/ng/schema/principalidwidget/configure.zcml
src/ng/schema/principalidwidget/principalidwidget.py
src/ng/schema/regexp/__init__.py
src/ng/schema/regexp/configure.zcml
src/ng/schema/regexp/interfaces.py
src/ng/schema/regexp/regexpfield.py